PSpincalc/PSpincalc.py
PSpincalc/__init__.py
examples/__init__.py
examples/examplesPSpincalc.py
tests/__init__.py
tests/tests.py
PSpincalc-0.2.7.dist-info/LICENSE.txt
PSpincalc-0.2.7.dist-info/METADATA
PSpincalc-0.2.7.dist-info/WHEEL
PSpincalc-0.2.7.dist-info/top_level.txt
PSpincalc-0.2.7.dist-info/RECORD
